xtlearn/__init__.py
xtlearn/__main__.py
xtlearn/feature_selection.py
xtlearn/linear_model.py
xtlearn/metrics.py
xtlearn/model_selection.py
xtlearn/preprocessing.py
xtlearn/utils.py
xtlearn/visualization.py
xtlearn-0.0.25.dist-info/LICENSE
xtlearn-0.0.25.dist-info/METADATA
xtlearn-0.0.25.dist-info/WHEEL
xtlearn-0.0.25.dist-info/top_level.txt
xtlearn-0.0.25.dist-info/RECORD
