Metadata-Version: 2.1
Name: xtlearn
Version: 0.0.25
Summary: This is a package with classes to be used in sklearn pipelines with pandas dataframes
Home-page: https://github.com/emdemor/xtlearn
Author: Eduardo M. de Morais
Author-email: emdemor415@gmail.com
License: MIT License
Keywords: preprocessing
Platform: UNKNOWN
License-File: LICENSE
Requires-Dist: numpy
Requires-Dist: scipy
Requires-Dist: pandas
Requires-Dist: setuptools
Requires-Dist: tqdm
Requires-Dist: scikit-learn
